os2mo_http_trigger_protocol/__init__.py
os2mo_http_trigger_protocol-0.0.4.dist-info/LICENSE
os2mo_http_trigger_protocol-0.0.4.dist-info/METADATA
os2mo_http_trigger_protocol-0.0.4.dist-info/WHEEL
os2mo_http_trigger_protocol-0.0.4.dist-info/top_level.txt
os2mo_http_trigger_protocol-0.0.4.dist-info/RECORD
