Metadata-Version: 2.1
Name: os2mo-http-trigger-protocol
Version: 0.0.4
Summary: Protocol library for OS2mo HTTP triggers
Home-page: https://git.magenta.dk/rammearkitektur/os2mo-http-trigger-protocol
Author: Magenta ApS
Author-email: info@magenta.dk
License: MPL 2.0
Platform: UNKNOWN
Classifier: Programming Language :: Python :: 3
Classifier: License :: OSI Approved :: Mozilla Public License 2.0 (MPL 2.0)
Classifier: Operating System :: OS Independent
Requires-Python: >=3.6
Requires-Dist: pydantic
Provides-Extra: dist
Requires-Dist: build ; extra == 'dist'
Requires-Dist: twine ; extra == 'dist'
Provides-Extra: lint
Requires-Dist: mypy ; extra == 'lint'
Requires-Dist: black ; extra == 'lint'
Requires-Dist: isort ; extra == 'lint'
Provides-Extra: test
Requires-Dist: pytest ; extra == 'test'
Requires-Dist: pytest-cov ; extra == 'test'
